{"source": "The New York Times", "lead_paragraph": "1. the longest division of geological time2. an immeasurably long period of time", "keywords": [{"rank": "1", "name": "type_of_material", "value": "News"}], "multimedia": [], "snippet": "This word has appeared in seven Times articles over the past year.", "print_page": null, "blog": [], "headline": {"kicker": "The Learning Network", "main": "Word of the Day | eon"}, "_id": "4fd39c8b8eb7c8105d8dcaee", "web_url": "http://learning.blogs.nytimes.com/2010/09/01/word-of-the-day-eon/", "slideshow_credits": null, "byline": {"organization": "THE LEARNING NETWORK", "person": [], "original": "By THE LEARNING NETWORK"}, "news_desk": null, "word_count": 101, "document_type": "blogpost", "type_of_material": "Blog", "abstract": "This word has appeared in seven Times articles over the past year.", "pub_date": "2010-09-01T00:45:55Z", "subsection_name": null, "section_name": "U.S."}