{"source": "The New York Times", "lead_paragraph": "North Korea called for an end to hostile relations with the United States in a New Year\u2019s message on Friday, the official news agency KCNA reported.", "keywords": [{"value": "North Korea", "rank": "1", "is_major": "N", "name": "glocations"}, {"value": "United States", "rank": "2", "is_major": "N", "name": "glocations"}, {"value": "International Relations", "rank": "3", "is_major": "N", "name": "subject"}], "multimedia": [], "snippet": "North Korea called for an end to hostile relations with the United States in a New Year\u2019s message on Friday, the official news agency KCNA reported.", "print_page": "12", "blog": [], "headline": {"content_kicker": "World Briefing | Asia", "main": "North Korea: A Message of Peace", "print_headline": "North Korea: A Message of Peace"}, "_id": "5424482438f0d8525e45318d", "web_url": "http://www.nytimes.com/2010/01/01/world/asia/01briefs-KoreaBrf.html", "slideshow_credits": null, "byline": {"organization": "REUTERS", "person": [], "original": "By REUTERS"}, "news_desk": "Foreign", "word_count": "110", "document_type": "article", "type_of_material": "Brief", "abstract": null, "pub_date": "2010-01-01T00:00:00Z", "subsection_name": "Asia Pacific", "section_name": "World"}