{"copyright": "Copyright (c) 2013 The New York Times Company.  All Rights Reserved.", "response": {"docs": [{"web_url": "http://www.nytimes.com/2016/08/28/fashion/weddings/ej-dickson-alex-la-ferla.html", "headline": {"main": "EJ Dickson, Alex La Ferla", "print_headline": "EJ Dickson,  Alex La Ferla"}, "snippet": "The bride, an editor, and the groom, an architectural designer, met at Oberlin College....", "document_type": "article", "abstract": null, "slideshow_credits": null, "pub_date": "2016-08-28T04:00:00+0000", "keywords": [{"rank": "1", "is_major": "N", "value": "Weddings and Engagements", "name": "subject"}], "print_page": null, "section_name": "Fashion & Style", "byline": [], "blog": [], "subsection_name": "Weddings", "_id": "57c2667995d0e021d7983027", "word_count": "192", "source": "The New York Times", "type_of_material": "News", "lead_paragraph": "The bride, an editor, and the groom, an architectural designer, met at Oberlin College.", "multimedia": [], "news_desk": "Society"}, {"web_url": "http://www.nytimes.com/2016/08/28/fashion/weddings/hadley-planting-alexander-powell.html", "headline": {"main": "Hadley Planting, Alexander Powell", "print_headline": "Hadley Planting,  Alexander Powell"}, "snippet": "The couple met in August 2014, at the Maine Seacoast Mission gala in Bar Harbor, Me....", "document_type": "article", "abstract": null, "slideshow_credits": null, "pub_date": "2016-08-28T04:00:00+0000", "keywords": [{"rank": "1", "is_major": "N", "value": "Weddings and Engagements", "name": "subject"}], "print_page": "16", "section_name": "Fashion & Style", "byline": [], "blog": [], "subsection_name": "Weddings", "_id": "57c2660495d0e021d7983026", "word_count": "271", "source": "The New York Times", "type_of_material": "News", "lead_paragraph": "The couple met in August 2014, at the Maine Seacoast Mission gala in Bar Harbor, Me.", "multimedia": [{"type": "image", "legacy": {"wide": "images/2016/08/28/fashion/weddings/28PLANTING/28PLANTING-thumbWide-v2.jpg", "wideheight": "126", "widewidth": "190"}, "width": 190, "height": 126, "url": "images/2016/08/28/fashion/weddings/28PLANTING/28PLANTING-thumbWide-v2.jpg", "subtype": "wide"}, {"type": "image", "legacy": {"xlargewidth": "600", "xlarge": "images/2016/08/28/fashion/weddings/28PLANTING/28PLANTING-articleLarge-v2.jpg", "xlargeheight": "354"}, "width": 600, "height": 354, "url": "images/2016/08/28/fashion/weddings/28PLANTING/28PLANTING-articleLarge-v2.jpg", "subtype": "xlarge"}, {"type": "image", "legacy": {"thumbnailwidth": "75", "thumbnail": "images/2016/08/28/fashion/weddings/28PLANTING/28PLANTING-thumbStandard.jpg", "thumbnailheight": "75"}, "width": 75, "height": 75, "url": "images/2016/08/28/fashion/weddings/28PLANTING/28PLANTING-thumbStandard.jpg", "subtype": "thumbnail"}], "news_desk": "Society"}, {"web_url": "http://www.nytimes.com/aponline/2016/08/28/us/ap-us-plane-crash-new-orleans.html", "headline": {"main": "Plane Found, 2 Still Missing After Crash in New Orleans Lake", "print_headline": "Plane Found, 2 Still Missing After Crash in New Orleans Lake"}, "snippet": "Divers found the wreckage of a small plane that crashed into the huge, mud-bottomed lake that forms New Orleans' northern shore, but two men remained missing Sunday, the New Orleans Fire Department said....", "document_type": "article", "abstract": null, "slideshow_credits": null, "pub_date": "2016-08-28T04:14:02Z", "keywords": [], "print_page": null, "section_name": "U.S.", "byline": {"person": [], "original": "By THE ASSOCIATED PRESS", "organization": "THE ASSOCIATED PRESS"}, "blog": [], "subsection_name": null, "_id": "57c2656a95d0e021d7983025", "word_count": null, "source": "", "type_of_material": "News", "lead_paragraph": "Divers found the wreckage of a small plane that crashed into the huge, mud-bottomed lake that forms New Orleans' northern shore, but two men remained missing Sunday, the New Orleans Fire Department said.", "multimedia": [], "news_desk": "None"}, {"web_url": "http://www.nytimes.com/2016/08/28/fashion/weddings/erin-hays-stan-chiueh.html", "headline": {"main": "Erin Hays, Stan Chiueh", "print_headline": "Erin Hays,  Stan Chiueh"}, "snippet": "The couple met at Yale but reconnected years later at a trivia night in New York....", "document_type": "article", "abstract": null, "slideshow_credits": null, "pub_date": "2016-08-28T04:00:00+0000", "keywords": [{"rank": "1", "is_major": "N", "value": "Weddings and Engagements", "name": "subject"}], "print_page": "17", "section_name": "Fashion & Style", "byline": [], "blog": [], "subsection_name": "Weddings", "_id": "57c2656595d0e021d7983023", "word_count": "227", "source": "The New York Times", "type_of_material": "News", "lead_paragraph": "The couple met at Yale but reconnected years later at a trivia night in New York.", "multimedia": [{"type": "image", "legacy": {"wide": "images/2016/08/28/fashion/weddings/28HAYS/28HAYS-thumbWide.jpg", "wideheight": "126", "widewidth": "190"}, "width": 190, "height": 126, "url": "images/2016/08/28/fashion/weddings/28HAYS/28HAYS-thumbWide.jpg", "subtype": "wide"}, {"type": "image", "legacy": {"xlargewidth": "600", "xlarge": "images/2016/08/28/fashion/weddings/28HAYS/28HAYS-articleLarge.jpg", "xlargeheight": "355"}, "width": 600, "height": 355, "url": "images/2016/08/28/fashion/weddings/28HAYS/28HAYS-articleLarge.jpg", "subtype": "xlarge"}, {"type": "image", "legacy": {"thumbnailwidth": "75", "thumbnail": "images/2016/08/28/fashion/weddings/28HAYS/28HAYS-thumbStandard.jpg", "thumbnailheight": "75"}, "width": 75, "height": 75, "url": "images/2016/08/28/fashion/weddings/28HAYS/28HAYS-thumbStandard.jpg", "subtype": "thumbnail"}], "news_desk": "Society"}, {"web_url": "http://www.nytimes.com/2016/08/28/fashion/weddings/shahrzad-daneshvar-travis-viola.html", "headline": {"main": "Shahrzad Daneshvar, Travis Viola", "print_headline": "Shahrzad Daneshvar,  Travis Viola"}, "snippet": "The couple were married in a Persian ceremony at the Waldorf Astoria in New York....", "document_type": "article", "abstract": null, "slideshow_credits": null, "pub_date": "2016-08-28T04:00:00+0000", "keywords": [{"rank": "1", "is_major": "N", "value": "Weddings and Engagements", "name": "subject"}], "print_page": "17", "section_name": "Fashion & Style", "byline": [], "blog": [], "subsection_name": "Weddings", "_id": "57c2656495d0e021d7983021", "word_count": "223", "source": "The New York Times", "type_of_material": "News", "lead_paragraph": "The couple were married in a Persian ceremony at the Waldorf Astoria in New York.", "multimedia": [{"type": "image", "legacy": {"wide": "images/2016/08/28/fashion/weddings/28DANESHVAR/28DANESHVAR-thumbWide.jpg", "wideheight": "126", "widewidth": "190"}, "width": 190, "height": 126, "url": "images/2016/08/28/fashion/weddings/28DANESHVAR/28DANESHVAR-thumbWide.jpg", "subtype": "wide"}, {"type": "image", "legacy": {"xlargewidth": "600", "xlarge": "images/2016/08/28/fashion/weddings/28DANESHVAR/28DANESHVAR-articleLarge.jpg", "xlargeheight": "354"}, "width": 600, "height": 354, "url": "images/2016/08/28/fashion/weddings/28DANESHVAR/28DANESHVAR-articleLarge.jpg", "subtype": "xlarge"}, {"type": "image", "legacy": {"thumbnailwidth": "75", "thumbnail": "images/2016/08/28/fashion/weddings/28DANESHVAR/28DANESHVAR-thumbStandard.jpg", "thumbnailheight": "75"}, "width": 75, "height": 75, "url": "images/2016/08/28/fashion/weddings/28DANESHVAR/28DANESHVAR-thumbStandard.jpg", "subtype": "thumbnail"}], "news_desk": "Society"}, {"web_url": "http://www.nytimes.com/2016/08/28/fashion/weddings/jill-brimmer-patrick-boland.html", "headline": {"main": "Jill Brimmer, Patrick Boland", "print_headline": "Jill Brimmer,  Patrick Boland"}, "snippet": "The bride works for Senator Jack Reed of Rhode Island and the groom for Representative Adam B. Schiff of California....", "document_type": "article", "abstract": null, "slideshow_credits": null, "pub_date": "2016-08-28T04:00:00+0000", "keywords": [{"rank": "1", "is_major": "N", "value": "Weddings and Engagements", "name": "subject"}], "print_page": "17", "section_name": "Fashion & Style", "byline": [], "blog": [], "subsection_name": "Weddings", "_id": "57c2656495d0e021d7983022", "word_count": "214", "source": "The New York Times", "type_of_material": "News", "lead_paragraph": "The bride works for Senator Jack Reed of Rhode Island and the groom for Representative Adam B. Schiff of California.", "multimedia": [{"type": "image", "legacy": {"wide": "images/2016/08/28/fashion/weddings/28BRIMMER/28BRIMMER-thumbWide.jpg", "wideheight": "126", "widewidth": "190"}, "width": 190, "height": 126, "url": "images/2016/08/28/fashion/weddings/28BRIMMER/28BRIMMER-thumbWide.jpg", "subtype": "wide"}, {"type": "image", "legacy": {"xlargewidth": "600", "xlarge": "images/2016/08/28/fashion/weddings/28BRIMMER/28BRIMMER-articleLarge.jpg", "xlargeheight": "354"}, "width": 600, "height": 354, "url": "images/2016/08/28/fashion/weddings/28BRIMMER/28BRIMMER-articleLarge.jpg", "subtype": "xlarge"}, {"type": "image", "legacy": {"thumbnailwidth": "75", "thumbnail": "images/2016/08/28/fashion/weddings/28BRIMMER/28BRIMMER-thumbStandard.jpg", "thumbnailheight": "75"}, "width": 75, "height": 75, "url": "images/2016/08/28/fashion/weddings/28BRIMMER/28BRIMMER-thumbStandard.jpg", "subtype": "thumbnail"}], "news_desk": "Society"}, {"web_url": "http://www.nytimes.com/2016/08/28/fashion/weddings/laurel-rapp-matthew-davis.html", "headline": {"main": "Laurel Rapp, Matthew Davis", "print_headline": "Laurel Rapp,  Matthew Davis"}, "snippet": "The couple met four years ago in Washington at a mutual friend\u2019s cocktail party....", "document_type": "article", "abstract": null, "slideshow_credits": null, "pub_date": "2016-08-28T04:00:00+0000", "keywords": [{"rank": "1", "is_major": "N", "value": "Weddings and Engagements", "name": "subject"}], "print_page": "17", "section_name": "Fashion & Style", "byline": [], "blog": [], "subsection_name": "Weddings", "_id": "57c2656795d0e021d7983024", "word_count": "187", "source": "The New York Times", "type_of_material": "News", "lead_paragraph": "The couple met four years ago in Washington at a mutual friend\u2019s cocktail party.", "multimedia": [{"type": "image", "legacy": {"wide": "images/2016/08/28/fashion/weddings/28RAPP/28RAPP-thumbWide.jpg", "wideheight": "126", "widewidth": "190"}, "width": 190, "height": 126, "url": "images/2016/08/28/fashion/weddings/28RAPP/28RAPP-thumbWide.jpg", "subtype": "wide"}, {"type": "image", "legacy": {"xlargewidth": "600", "xlarge": "images/2016/08/28/fashion/weddings/28RAPP/28RAPP-articleLarge.jpg", "xlargeheight": "450"}, "width": 600, "height": 450, "url": "images/2016/08/28/fashion/weddings/28RAPP/28RAPP-articleLarge.jpg", "subtype": "xlarge"}, {"type": "image", "legacy": {"thumbnailwidth": "75", "thumbnail": "images/2016/08/28/fashion/weddings/28RAPP/28RAPP-thumbStandard.jpg", "thumbnailheight": "75"}, "width": 75, "height": 75, "url": "images/2016/08/28/fashion/weddings/28RAPP/28RAPP-thumbStandard.jpg", "subtype": "thumbnail"}], "news_desk": "Society"}, {"web_url": "http://www.nytimes.com/2016/08/28/fashion/weddings/sarah-fecht-charles-choi.html", "headline": {"main": "Sarah Fecht, Charles Choi", "print_headline": "Sarah Fecht,  Charles Choi"}, "snippet": "She is an assistant editor for Popular Science\u2019s website. He is a freelance science writer....", "document_type": "article", "abstract": null, "slideshow_credits": null, "pub_date": "2016-08-28T04:00:00+0000", "keywords": [{"rank": "1", "is_major": "N", "value": "Weddings and Engagements", "name": "subject"}, {"rank": "2", "is_major": "N", "value": "Popular Science", "name": "organizations"}], "print_page": "16", "section_name": "Fashion & Style", "byline": [], "blog": [], "subsection_name": "Weddings", "_id": "57c2654e95d0e021d798301d", "word_count": "145", "source": "The New York Times", "type_of_material": "News", "lead_paragraph": "She is an assistant editor for Popular Science\u2019s website. He is a freelance science writer.", "multimedia": [{"type": "image", "legacy": {"wide": "images/2016/08/28/fashion/weddings/28FECHT/28FECHT-thumbWide.jpg", "wideheight": "126", "widewidth": "190"}, "width": 190, "height": 126, "url": "images/2016/08/28/fashion/weddings/28FECHT/28FECHT-thumbWide.jpg", "subtype": "wide"}, {"type": "image", "legacy": {"xlargewidth": "600", "xlarge": "images/2016/08/28/fashion/weddings/28FECHT/28FECHT-articleLarge.jpg", "xlargeheight": "353"}, "width": 600, "height": 353, "url": "images/2016/08/28/fashion/weddings/28FECHT/28FECHT-articleLarge.jpg", "subtype": "xlarge"}, {"type": "image", "legacy": {"thumbnailwidth": "75", "thumbnail": "images/2016/08/28/fashion/weddings/28FECHT/28FECHT-thumbStandard.jpg", "thumbnailheight": "75"}, "width": 75, "height": 75, "url": "images/2016/08/28/fashion/weddings/28FECHT/28FECHT-thumbStandard.jpg", "subtype": "thumbnail"}], "news_desk": "Society"}, {"web_url": "http://www.nytimes.com/2016/08/28/fashion/weddings/jillian-colbert-sebastian-alsheimer.html", "headline": {"main": "Jillian Colbert, Sebastian Alsheimer", "print_headline": "Jillian Colbert, Sebastian Alsheimer"}, "snippet": "The couple met at Columbia, from which each received a law degree....", "document_type": "article", "abstract": null, "slideshow_credits": null, "pub_date": "2016-08-28T04:00:00+0000", "keywords": [{"rank": "1", "is_major": "N", "value": "Weddings and Engagements", "name": "subject"}], "print_page": "17", "section_name": "Fashion & Style", "byline": [], "blog": [], "subsection_name": "Weddings", "_id": "57c2654e95d0e021d798301c", "word_count": "231", "source": "The New York Times", "type_of_material": "News", "lead_paragraph": "The couple met at Columbia, from which each received a law degree.", "multimedia": [{"type": "image", "legacy": {"wide": "images/2016/08/28/fashion/weddings/28COLBERT/28COLBERT-thumbWide.jpg", "wideheight": "126", "widewidth": "190"}, "width": 190, "height": 126, "url": "images/2016/08/28/fashion/weddings/28COLBERT/28COLBERT-thumbWide.jpg", "subtype": "wide"}, {"type": "image", "legacy": {"xlargewidth": "600", "xlarge": "images/2016/08/28/fashion/weddings/28COLBERT/28COLBERT-articleLarge.jpg", "xlargeheight": "355"}, "width": 600, "height": 355, "url": "images/2016/08/28/fashion/weddings/28COLBERT/28COLBERT-articleLarge.jpg", "subtype": "xlarge"}, {"type": "image", "legacy": {"thumbnailwidth": "75", "thumbnail": "images/2016/08/28/fashion/weddings/28COLBERT/28COLBERT-thumbStandard.jpg", "thumbnailheight": "75"}, "width": 75, "height": 75, "url": "images/2016/08/28/fashion/weddings/28COLBERT/28COLBERT-thumbStandard.jpg", "subtype": "thumbnail"}], "news_desk": "Society"}, {"web_url": "http://www.nytimes.com/2016/08/28/fashion/weddings/jennifer-nedeau-austin-helm.html", "headline": {"main": "Jennifer Nedeau, Austin Helm", "print_headline": "Jennifer Nedeau,  Austin Helm"}, "snippet": "The bride, who works for an advertising firm, and the groom, who works for a business consulting firm, met in a Washington bar....", "document_type": "article", "abstract": null, "slideshow_credits": null, "pub_date": "2016-08-28T04:00:00+0000", "keywords": [{"rank": "1", "is_major": "N", "value": "Weddings and Engagements", "name": "subject"}], "print_page": "17", "section_name": "Fashion & Style", "byline": [], "blog": [], "subsection_name": "Weddings", "_id": "57c2655195d0e021d798301f", "word_count": "225", "source": "The New York Times", "type_of_material": "News", "lead_paragraph": "The bride, who works for an advertising firm, and the groom, who works for a business consulting firm, met in a Washington bar.", "multimedia": [{"type": "image", "legacy": {"wide": "images/2016/08/28/fashion/weddings/28NEDEAU/28NEDEAU-thumbWide.jpg", "wideheight": "126", "widewidth": "190"}, "width": 190, "height": 126, "url": "images/2016/08/28/fashion/weddings/28NEDEAU/28NEDEAU-thumbWide.jpg", "subtype": "wide"}, {"type": "image", "legacy": {"xlargewidth": "600", "xlarge": "images/2016/08/28/fashion/weddings/28NEDEAU/28NEDEAU-articleLarge.jpg", "xlargeheight": "354"}, "width": 600, "height": 354, "url": "images/2016/08/28/fashion/weddings/28NEDEAU/28NEDEAU-articleLarge.jpg", "subtype": "xlarge"}, {"type": "image", "legacy": {"thumbnailwidth": "75", "thumbnail": "images/2016/08/28/fashion/weddings/28NEDEAU/28NEDEAU-thumbStandard.jpg", "thumbnailheight": "75"}, "width": 75, "height": 75, "url": "images/2016/08/28/fashion/weddings/28NEDEAU/28NEDEAU-thumbStandard.jpg", "subtype": "thumbnail"}], "news_desk": "Society"}], "meta": {"time": 38, "offset": 280, "hits": 473}}, "status": "OK"}